genetic_selection/__init__.py
genetic_selection/gscv.py
genetic_selection/tests/__init__.py
genetic_selection/tests/test_selection.py
sklearn_genetic-0.6.0.dist-info/LICENSE.txt
sklearn_genetic-0.6.0.dist-info/METADATA
sklearn_genetic-0.6.0.dist-info/WHEEL
sklearn_genetic-0.6.0.dist-info/top_level.txt
sklearn_genetic-0.6.0.dist-info/RECORD
