Metadata-Version: 2.1
Name: sklearn-genetic
Version: 0.6.0
Summary: Genetic feature selection module for scikit-learn
Home-page: https://github.com/manuel-calzolari/sklearn-genetic
Download-URL: https://github.com/manuel-calzolari/sklearn-genetic/releases
Author: Manuel Calzolari
Classifier: Development Status :: 4 - Beta
Classifier: Intended Audience :: Science/Research
Classifier: Intended Audience :: Developers
Classifier: Topic :: Software Development
Classifier: Topic :: Scientific/Engineering
Classifier: License :: OSI Approved :: GNU Lesser General Public License v3 (LGPLv3)
Classifier: Programming Language :: Python :: 3
Classifier: Programming Language :: Python :: 3.7
Classifier: Programming Language :: Python :: 3.8
Classifier: Programming Language :: Python :: 3.9
Classifier: Programming Language :: Python :: 3.10
Classifier: Programming Language :: Python :: 3.11
Requires-Python: >=3.7
License-File: LICENSE.txt
Requires-Dist: scikit-learn >=1.0
Requires-Dist: deap >=1.0.2
Requires-Dist: numpy
Requires-Dist: multiprocess
